giga_spatial-0.7.3.dist-info/licenses/LICENSE
gigaspatial/__init__.py
gigaspatial/config.py
gigaspatial/core/__init__.py
gigaspatial/core/io/__init__.py
gigaspatial/core/io/adls_data_store.py
gigaspatial/core/io/data_api.py
gigaspatial/core/io/data_store.py
gigaspatial/core/io/database.py
gigaspatial/core/io/local_data_store.py
gigaspatial/core/io/readers.py
gigaspatial/core/io/snowflake_data_store.py
gigaspatial/core/io/writers.py
gigaspatial/core/schemas/__init__.py
gigaspatial/core/schemas/entity.py
gigaspatial/generators/__init__.py
gigaspatial/generators/poi.py
gigaspatial/generators/zonal/__init__.py
gigaspatial/generators/zonal/admin.py
gigaspatial/generators/zonal/base.py
gigaspatial/generators/zonal/geometry.py
gigaspatial/generators/zonal/h3.py
gigaspatial/generators/zonal/mercator.py
gigaspatial/generators/zonal/s2.py
gigaspatial/grid/__init__.py
gigaspatial/grid/h3.py
gigaspatial/grid/mercator_tiles.py
gigaspatial/grid/s2.py
gigaspatial/handlers/__init__.py
gigaspatial/handlers/base.py
gigaspatial/handlers/boundaries.py
gigaspatial/handlers/ghsl.py
gigaspatial/handlers/giga.py
gigaspatial/handlers/google_open_buildings.py
gigaspatial/handlers/hdx.py
gigaspatial/handlers/healthsites.py
gigaspatial/handlers/mapbox_image.py
gigaspatial/handlers/maxar_image.py
gigaspatial/handlers/microsoft_global_buildings.py
gigaspatial/handlers/ookla_speedtest.py
gigaspatial/handlers/opencellid.py
gigaspatial/handlers/osm.py
gigaspatial/handlers/overture.py
gigaspatial/handlers/rwi.py
gigaspatial/handlers/unicef_georepo.py
gigaspatial/handlers/worldpop.py
gigaspatial/handlers/srtm/__init__.py
gigaspatial/handlers/srtm/nasa_srtm.py
gigaspatial/handlers/srtm/srtm_manager.py
gigaspatial/handlers/srtm/srtm_parser.py
gigaspatial/handlers/srtm/utils.py
gigaspatial/processing/__init__.py
gigaspatial/processing/algorithms.py
gigaspatial/processing/geo.py
gigaspatial/processing/sat_images.py
gigaspatial/processing/tif_processor.py
gigaspatial/processing/utils.py
giga_spatial-0.7.3.dist-info/METADATA
giga_spatial-0.7.3.dist-info/WHEEL
giga_spatial-0.7.3.dist-info/top_level.txt
giga_spatial-0.7.3.dist-info/RECORD
