Metadata-Version: 2.4
Name: giga-spatial
Version: 0.7.3
Summary: A package for spatial data download & processing
Author: Utku Can Ozturk
Author-email: utkucanozturk@gmail.com
License: AGPL-3.0-or-later
Project-URL: Homepage, https://github.com/unicef/giga-spatial
Project-URL: Documentation, https://unicef.github.io/giga-spatial/
Project-URL: Source, https://github.com/unicef/giga-spatial
Project-URL: Issue Tracker, https://github.com/unicef/giga-spatial/issues
Project-URL: Discussions, https://github.com/unicef/giga-spatial/discussions
Project-URL: Changelog, https://unicef.github.io/giga-spatial/changelog
Keywords: gigaspatial,spatial,geospatial,gis,remote sensing,data processing,download,openstreetmap,osm,ghsl,grid,point of interest,POI,raster,vector,school connectivity,unicef,giga,mapping,analysis,python
Classifier: Development Status :: 5 - Production/Stable
Classifier: Intended Audience :: Developers
Classifier: Intended Audience :: Education
Classifier: Intended Audience :: Healthcare Industry
Classifier: Intended Audience :: Science/Research
Classifier: Intended Audience :: Telecommunications Industry
Classifier: Programming Language :: Python
Classifier: Programming Language :: Python :: 3
Classifier: Programming Language :: Python :: 3.10
Classifier: Programming Language :: Python :: 3.11
Classifier: Programming Language :: Python :: 3.12
Classifier: Topic :: Scientific/Engineering :: GIS
Classifier: License :: OSI Approved :: GNU Affero General Public License v3
Classifier: Operating System :: OS Independent
Requires-Python: >=3.10
License-File: LICENSE
Requires-Dist: azure-storage-blob>=12.22.0
Requires-Dist: delta_sharing==1.2.0
Requires-Dist: duckdb==1.2.0
Requires-Dist: geopandas>=1.0.1
Requires-Dist: mercantile==1.2.1
Requires-Dist: numpy>=2.2.2
Requires-Dist: pandas>=2.2.3
Requires-Dist: pycountry==24.6.1
Requires-Dist: pydantic>=2.10.6
Requires-Dist: rasterio==1.3.10
Requires-Dist: Requests==2.32.3
Requires-Dist: scipy>=1.15.1
Requires-Dist: Shapely>=2.0.7
Requires-Dist: networkx>=3.2.1
Requires-Dist: tqdm==4.65.0
Requires-Dist: OWSLib==0.32.1
Requires-Dist: pydantic-settings>=2.7.1
Requires-Dist: hdx-python-api>=6.3.8
Requires-Dist: bs4==0.0.2
Requires-Dist: sqlalchemy-trino==0.5.0
Requires-Dist: dask>=2024.12.1
Requires-Dist: h3>=4.2.0
Requires-Dist: s2sphere==0.2.5
Requires-Dist: snowflake-connector-python>=3.0.0
Dynamic: author
Dynamic: author-email
Dynamic: classifier
Dynamic: description
Dynamic: description-content-type
Dynamic: keywords
Dynamic: license
Dynamic: license-file
Dynamic: project-url
Dynamic: requires-dist
Dynamic: requires-python
Dynamic: summary
